setup.py
shinkenplugins/__init__.py
shinkenplugins.plugins.linux_traffic.egg-info/PKG-INFO
shinkenplugins.plugins.linux_traffic.egg-info/SOURCES.txt
shinkenplugins.plugins.linux_traffic.egg-info/dependency_links.txt
shinkenplugins.plugins.linux_traffic.egg-info/entry_points.txt
shinkenplugins.plugins.linux_traffic.egg-info/namespace_packages.txt
shinkenplugins.plugins.linux_traffic.egg-info/requires.txt
shinkenplugins.plugins.linux_traffic.egg-info/top_level.txt
shinkenplugins/plugins/__init__.py
shinkenplugins/plugins/linux_traffic/__init__.py
shinkenplugins/plugins/linux_traffic/linux_traffic.py