Metadata-Version: 1.0
Name: shinkenplugins.plugins.linux-traffic
Version: 1.2
Summary: Check Linux traffic
Home-page: https://github.com/savoirfairelinux/sfl-shinken-plugins
Author: Grégory Starck
Author-email: gregory.starck@savoirfairelinux.com
License: GPL3+
Platform: any
